{
  "name": "articles/ΣΥΝΕΝΤΕΥΞΗ-Γνωρίστε-τους-Thy-Legion-el.json",
  "bucket": "heavy-local-12bc4.appspot.com",
  "metageneration": 1,
  "generation": 1720119292954,
  "contentType": "application/json",
  "storageClass": "STANDARD",
  "contentDisposition": "inline",
  "downloadTokens": [
    "54457570-47af-4eb0-a440-6d2eb683f65c"
  ],
  "etag": "YJ7YO1MSQQ6EvNKIuCiWVFbwm3o",
  "customMetadata": {},
  "timeCreated": "2024-07-04T18:54:52.954Z",
  "updated": "2024-07-04T18:54:52.954Z",
  "size": 10179,
  "md5Hash": "/iEvp9+K6XnUFG2Dy8nAAw==",
  "crc32c": "3962325449"
}