{
  "name": "images/Concerts/workInProgress/DSC_0028_600x300.JPG",
  "bucket": "heavy-local-12bc4.appspot.com",
  "metageneration": 2,
  "generation": 1720125595796,
  "contentType": "image/jpeg",
  "storageClass": "STANDARD",
  "contentDisposition": "inline",
  "downloadTokens": [
    "fe2e9602-9ad1-4e96-be06-2a918744ee7f"
  ],
  "etag": "CnUe9nF+kt5N6XEYYYh3YXXewv0",
  "customMetadata": {
    "width": "600",
    "height": "300"
  },
  "timeCreated": "2024-07-04T20:39:55.796Z",
  "updated": "2024-07-04T20:39:57.046Z",
  "size": 39974,
  "md5Hash": "jeNmf1tN1Rwtpc5rqw6PVQ==",
  "crc32c": "1616238950"
}