{
  "name": "gigs/2024_03_15/17_600x600.jpg",
  "bucket": "heavy-local-12bc4.appspot.com",
  "metageneration": 2,
  "generation": 1720284564914,
  "contentType": "image/jpeg",
  "storageClass": "STANDARD",
  "contentDisposition": "inline",
  "downloadTokens": [
    "e2dfe6d6-47ce-4006-9842-bf00129debb4"
  ],
  "etag": "clAQS3LN0Mz1LHZpgN14dkN0uW8",
  "customMetadata": {
    "width": "600",
    "height": "600"
  },
  "timeCreated": "2024-07-06T16:49:24.914Z",
  "updated": "2024-07-06T16:49:44.732Z",
  "size": 47502,
  "md5Hash": "HM9idO5eYkosL06MJ5uL9Q==",
  "crc32c": "3522241697"
}